rawsec_cli/__init__.py
rawsec_cli/filter.py
rawsec_cli/output.py
rawsec_cli/search.py
rawsec_cli/tools.py
rawsec_cli/cli/__init__.py
rawsec_cli/cli/cli.py
rawsec_cli/cli/command/__init__.py
rawsec_cli/cli/command/list_command.py
rawsec_cli/cli/command/search_command.py
tests/__init__.py
tests/test_filter.py
tests/test_output.py
tests/test_search.py
tests/test_tools.py
tests/cli/__init__.py
tests/cli/test_cli.py
tests/cli/command/__init__.py
tests/cli/command/test_list_command.py
tests/cli/command/test_search_command.py
rawsec_cli-1.2.0.dist-info/LICENSE
rawsec_cli-1.2.0.dist-info/METADATA
rawsec_cli-1.2.0.dist-info/WHEEL
rawsec_cli-1.2.0.dist-info/entry_points.txt
rawsec_cli-1.2.0.dist-info/top_level.txt
rawsec_cli-1.2.0.dist-info/RECORD
