Metadata-Version: 2.1
Name: rawsec-cli
Version: 1.2.0
Summary: Cli for searching tools & resources on rawsec's CyberSecrity Inventory
Home-page: https://github.com/mBouamama/rawsec_cli
Author: mBouamama
Author-email: matthieubouamama@gmail.com
License: UNKNOWN
Platform: UNKNOWN
Classifier: Development Status :: 5 - Production/Stable
Classifier: Environment :: Console
Classifier: Intended Audience :: Developers
Classifier: License :: OSI Approved :: MIT License
Classifier: Operating System :: OS Independent
Classifier: Programming Language :: Python :: 3
Classifier: Programming Language :: Python
Classifier: Programming Language :: Python :: 3 :: Only
Classifier: Programming Language :: Python :: 3.6
Classifier: Programming Language :: Python :: 3.7
Classifier: Programming Language :: Python :: 3.8
Classifier: Programming Language :: Python :: 3.9
Classifier: Topic :: Security
Classifier: Topic :: Internet :: WWW/HTTP
Requires-Python: >=3.6
Requires-Dist: click (==8.0.1)
Requires-Dist: Columnar (==1.3.1)
Requires-Dist: gitpython (==3.1.17)
Requires-Dist: requests (==2.25.1)
Requires-Dist: tabulate (==0.8.9)
Provides-Extra: dev
Requires-Dist: coverage (==5.5) ; extra == 'dev'
Requires-Dist: flake8 (==3.9.2) ; extra == 'dev'
Requires-Dist: pre-commit (==2.13.0) ; extra == 'dev'
Requires-Dist: pytest (==6.2.4) ; extra == 'dev'
Requires-Dist: pytest-mock (==3.6.1) ; extra == 'dev'
Requires-Dist: requests-mock (==1.9.3) ; extra == 'dev'
Provides-Extra: docs
Requires-Dist: recommonmark (==0.7.1) ; extra == 'docs'
Requires-Dist: Sphinx (==4.0.2) ; extra == 'docs'
Requires-Dist: sphinx-markdown-tables (==0.0.15) ; extra == 'docs'
Requires-Dist: sphinx-rtd-theme (==0.5.2) ; extra == 'docs'
